mklist/__init__.py
mklist/cli.py
mklist/generate.py
pymklist-1.1.0.dist-info/LICENSE
pymklist-1.1.0.dist-info/METADATA
pymklist-1.1.0.dist-info/WHEEL
pymklist-1.1.0.dist-info/entry_points.txt
pymklist-1.1.0.dist-info/top_level.txt
pymklist-1.1.0.dist-info/RECORD
