Metadata-Version: 2.1
Name: pymklist
Version: 1.1.0
Summary: LDraw mklist in Python
Home-page: https://github.com/rienafairefr/pymklist
Author: Matthieu Berthomé
Author-email: rienafairefr@gmail.com
License: GNU General Public License v3
Keywords: pymklist
Platform: UNKNOWN
Classifier: Development Status :: 2 - Pre-Alpha
Classifier: Intended Audience :: Developers
Classifier: License :: OSI Approved :: GNU General Public License v3 (GPLv3)
Classifier: Natural Language :: English
Classifier: Programming Language :: Python :: 3
Classifier: Programming Language :: Python :: 3.5
Classifier: Programming Language :: Python :: 3.5
Classifier: Programming Language :: Python :: 3.6
Classifier: Programming Language :: Python :: 3.7
Classifier: Programming Language :: Python :: 3.8
Classifier: Programming Language :: Python :: 3.9
Requires-Dist: Click (>=6.0)
